matriz/util.py
matriz/__init__.py
matriz/emitter.py
matriz/client.py
matriz/receiver.py
matriz/jack_client.py
matriz/config_server.py
matriz/monitor.py
matriz-0.2.7.dist-info/RECORD
matriz-0.2.7.dist-info/entry_points.txt
matriz-0.2.7.dist-info/METADATA
matriz-0.2.7.dist-info/WHEEL
matriz-0.2.7.dist-info/metadata.json
matriz-0.2.7.dist-info/top_level.txt
matriz-0.2.7.dist-info/DESCRIPTION.rst
