Metadata-Version: 2.0
Name: matriz
Version: 0.2.7
Summary: Networked Music Performance software
Home-page: https://github.com/stressfm/matriz
Author: Cláudio Rego, Hugo Martiniano, Vasco Pita
Author-email: claudiojmrego@gmail.com, hugomartiniano@gmail.com, vasco.pitaf@gmail.com
License: Type license() to see the full license text
Keywords: matriz,networked music performance
Platform: UNKNOWN
Classifier: Development Status :: 4 - Beta
Classifier: Environment :: Console
Classifier: Intended Audience :: Developers
Classifier: Topic :: Artistic Software
Classifier: Topic :: Education
Classifier: Topic :: Multimedia :: Sound/Audio
Classifier: Topic :: Other/Nonlisted Topic
Classifier: Topic :: Software Development
Classifier: Topic :: Utilities
Classifier: Intended Audience :: Education
Classifier: Intended Audience :: End Users/Desktop
Classifier: Intended Audience :: Other Audience
Classifier: License :: OSI Approved :: GNU General Public License v3 or later (GPLv3+)
Classifier: Natural Language :: English
Classifier: Programming Language :: Python :: 2
Classifier: Programming Language :: Python :: 2.7
Classifier: Programming Language :: Python :: 3
Classifier: Programming Language :: Python :: 3.4
Classifier: Programming Language :: Python :: Implementation :: CPython
Classifier: Programming Language :: Python :: Implementation :: PyPy
Requires-Dist: argparse (==1.2.1)
Requires-Dist: decorator (==3.4.0)
Requires-Dist: wheel (==0.24.0)
Requires-Dist: backports.ssl-match-hostname (==3.5.0.1)
Requires-Dist: six (==1.10.0)
Requires-Dist: websocket-client (==0.35.0)
Requires-Dist: wheel (==0.24.0)
Requires-Dist: JACK-Client (==0.4.0)
Requires-Dist: miniupnpc (==1.9)
Provides-Extra: server
Requires-Dist: Flask; extra == 'server'
Requires-Dist: Flask-uWSGI-WebSocket; extra == 'server'
Requires-Dist: gevent; extra == 'server'
Requires-Dist: greenlet; extra == 'server'
Requires-Dist: itsdangerous; extra == 'server'
Requires-Dist: Jinja2; extra == 'server'
Requires-Dist: MarkupSafe; extra == 'server'
Requires-Dist: uWSGI; extra == 'server'
Requires-Dist: Werkzeug; extra == 'server'
